Metadata-Version: 1.1
Name: printandredirect
Version: 0.0.1
Summary: simple pageredirect function
Home-page: UNKNOWN
Author: madhanreddy
Author-email: srimadhanreddy.1995@gmail.com
License: MIT
Keywords: validateandgreet
Platform: UNKNOWN
Classifier: Development Status :: 5 - Production/Stable
Classifier: Intended Audience :: Education
Classifier: Operating System :: Microsoft :: Windows :: Windows 10
Classifier: License :: OSI Approved :: MIT License
Classifier: Programming Language :: Python :: 3
